charset_normalizer/__init__.py
charset_normalizer/__main__.py
charset_normalizer/api.py
charset_normalizer/cd.py
charset_normalizer/constant.py
charset_normalizer/legacy.py
charset_normalizer/md.py
charset_normalizer/models.py
charset_normalizer/py.typed
charset_normalizer/utils.py
charset_normalizer/version.py
charset_normalizer/cli/__init__.py
charset_normalizer/cli/__main__.py
charset_normalizer-3.3.1.dist-info/LICENSE
charset_normalizer-3.3.1.dist-info/METADATA
charset_normalizer-3.3.1.dist-info/WHEEL
charset_normalizer-3.3.1.dist-info/entry_points.txt
charset_normalizer-3.3.1.dist-info/top_level.txt
charset_normalizer-3.3.1.dist-info/RECORD
