Metadata-Version: 2.1
Name: charset-normalizer
Version: 3.3.1
Summary: The Real First Universal Charset Detector. Open, modern and actively maintained alternative to Chardet.
Home-page: https://github.com/Ousret/charset_normalizer
Author: Ahmed TAHRI
Author-email: ahmed.tahri@cloudnursery.dev
License: MIT
Project-URL: Bug Reports, https://github.com/Ousret/charset_normalizer/issues
Project-URL: Documentation, https://charset-normalizer.readthedocs.io/en/latest
Keywords: encoding,charset,charset-detector,detector,normalization,unicode,chardet,detect
Classifier: Development Status :: 5 - Production/Stable
Classifier: License :: OSI Approved :: MIT License
Classifier: Intended Audience :: Developers
Classifier: Topic :: Software Development :: Libraries :: Python Modules
Classifier: Operating System :: OS Independent
Classifier: Programming Language :: Python
Classifier: Programming Language :: Python :: 3
Classifier: Programming Language :: Python :: 3.7
Classifier: Programming Language :: Python :: 3.8
Classifier: Programming Language :: Python :: 3.9
Classifier: Programming Language :: Python :: 3.10
Classifier: Programming Language :: Python :: 3.11
Classifier: Programming Language :: Python :: 3.12
Classifier: Programming Language :: Python :: Implementation :: PyPy
Classifier: Topic :: Text Processing :: Linguistic
Classifier: Topic :: Utilities
Classifier: Typing :: Typed
Requires-Python: >=3.7.0
License-File: LICENSE
Provides-Extra: unicode-backport
